rapidpro_api/__init__.py
rapidpro_api/contact_processors.py
rapidpro_api/contact_processors_pl.py
rapidpro_api/field_processors.py
rapidpro_api/flow_processors.py
rapidpro_api/group_processors.py
rapidpro_api/message_processors.py
rapidpro_api/run_processors_pl.py
rapidpro_api/telegram.py
rapidpro_api/time_utils.py
rapidpro_api/ureport_processors_pl.py
rapidpro_api/utils.py
rapidpro_api/validators.py
rapidpro_api/version.py
rapidpro_api/workspaces.py
rapidpro_api/datasets/BaseDataset.py
rapidpro_api/datasets/ContactsDataset.py
rapidpro_api/datasets/DeltaLakeDataset.py
rapidpro_api/datasets/FieldsDataset.py
rapidpro_api/datasets/FlowsDataset.py
rapidpro_api/datasets/GroupsDataset.py
rapidpro_api/datasets/MessagesDataset.py
rapidpro_api/datasets/RawDataset.py
rapidpro_api/datasets/RunsDataset.py
rapidpro_api/datasets/__init__.py
rapidpro_api/stats/__init__.py
rapidpro_api/stats/download_stats.py
rapidpro_api/stats/download_stats_list.py
rapidpro_api/stats/process_stats.py
rapidpro_api/stats/process_stats_list.py
rapidpro_api/stats/stats.py
tests/__init__.py
tests/test_contact_processors.py
tests/test_contact_processors_pl.py
tests/test_field_processors.py
tests/test_flow_processor.py
tests/test_group_processors.py
tests/test_message_processors.py
tests/test_run_processors_pl.py
tests/test_telegram.py
tests/test_time_utils.py
tests/test_ureport_processors_pl.py
tests/test_utils.py
tests/test_validators.py
tests/test_version.py
tests/test_workspaces.py
tests/datasets/__init__.py
tests/datasets/test_base_dataset.py
tests/datasets/test_contacts_dataset.py
tests/datasets/test_fields_dataset.py
tests/datasets/test_flows_dataset.py
tests/datasets/test_groups_dataset.py
tests/datasets/test_messages_dataset.py
tests/datasets/test_raw_dataset.py
tests/datasets/test_runs_dataset.py
tests/stats/__init__.py
tests/stats/test_download_stats.py
tests/stats/test_download_stats_list.py
tests/stats/test_process_stats.py
tests/stats/test_process_stats_list.py
tests/stats/test_stats.py
rapidpro_api-0.1.1.dist-info/METADATA
rapidpro_api-0.1.1.dist-info/WHEEL
rapidpro_api-0.1.1.dist-info/top_level.txt
rapidpro_api-0.1.1.dist-info/RECORD
